mcp2mqtt/__init__.py
mcp2mqtt/server.py
mcp2mqtt-0.3.0.dist-info/METADATA
mcp2mqtt-0.3.0.dist-info/WHEEL
mcp2mqtt-0.3.0.dist-info/entry_points.txt
mcp2mqtt-0.3.0.dist-info/licenses/LICENSE
mcp2mqtt-0.3.0.dist-info/RECORD
