Metadata-Version: 2.4
Name: mcp2mqtt
Version: 0.3.0
Summary: MCP MQTT Service for PWM Control and Device Communication
Project-URL: Homepage, https://github.com/mcp2everything/mcp2mqtt
Project-URL: Repository, https://github.com/mcp2everything/mcp2mqtt.git
Project-URL: Issues, https://github.com/mcp2everything/mcp2mqtt/issues
Project-URL: Changelog, https://github.com/mcp2everything/mcp2mqtt/blob/main/CHANGELOG.md
Author-email: mcp2everything <mcp2everything@gmail.com>
Maintainer-email: mcp2everything <mcp2everything@gmail.com>
License-Expression: MIT
License-File: LICENSE
Keywords: communication,control,device,mcp,mqtt,pwm
Classifier: Development Status :: 4 - Beta
Classifier: License :: OSI Approved :: MIT License
Classifier: Operating System :: OS Independent
Classifier: Programming Language :: Python :: 3
Requires-Python: >=3.10
Requires-Dist: httpx>=0.28.1
Requires-Dist: mcp-python>=0.1.0
Requires-Dist: mcp>=1.1.2
Requires-Dist: paho-mqtt>=1.6.1
Requires-Dist: pyyaml>=6.0.1
Provides-Extra: dev
Requires-Dist: pytest>=7.4.3; extra == 'dev'
